ModelStash/__init__.py
modelstash-1.0.1.dist-info/METADATA
modelstash-1.0.1.dist-info/WHEEL
modelstash-1.0.1.dist-info/licenses/LICENSE
modelstash-1.0.1.dist-info/RECORD
