Metadata-Version: 2.4
Name: ModelStash
Version: 1.0.1
Summary: A Python wrapper for OpenAI-compatible APIs with cost tracking and async/sync support
Project-URL: Homepage, https://github.com/BytePengwin/ModelStash
Project-URL: Repository, https://github.com/BytePengwin/ModelStash.git
Author: BytePengwin
License: GPL-3.0-only
License-File: LICENSE
Keywords: api,cost-tracking,llm,openai
Classifier: Development Status :: 5 - Production/Stable
Classifier: Intended Audience :: Developers
Classifier: License :: OSI Approved :: GNU General Public License v3 (GPLv3)
Classifier: Programming Language :: Python :: 3
Classifier: Programming Language :: Python :: 3.13
Classifier: Topic :: Software Development :: Libraries :: Python Modules
Requires-Python: >=3.13
Requires-Dist: httpx>=0.28.1
